pyiron_lammps/__init__.py
pyiron_lammps/_version.py
pyiron_lammps/output.py
pyiron_lammps/output_raw.py
pyiron_lammps/potential.py
pyiron_lammps/structure.py
pyiron_lammps/units.py
pyiron_lammps/compatibility/__init__.py
pyiron_lammps/compatibility/calculate.py
pyiron_lammps/compatibility/constraints.py
pyiron_lammps/compatibility/file.py
pyiron_lammps/compatibility/structure.py
pyiron_lammps-0.5.4.dist-info/METADATA
pyiron_lammps-0.5.4.dist-info/WHEEL
pyiron_lammps-0.5.4.dist-info/licenses/LICENSE
pyiron_lammps-0.5.4.dist-info/RECORD
