Metadata-Version: 2.4
Name: pyiron_lammps
Version: 0.5.4
Summary: Vector-oriented LAMMPS interface to rapidly iterate over series of atomistic structures or interatomic potentials.
Project-URL: Homepage, https://github.com/pyiron/pyiron_lammps
Project-URL: Documentation, https://github.com/pyiron/pyiron_lammps
Project-URL: Repository, https://github.com/pyiron/pyiron_lammps
Author-email: Jan Janssen <janssen@mpie.de>
License: BSD 3-Clause License
License-File: LICENSE
Keywords: pyiron
Classifier: Development Status :: 5 - Production/Stable
Classifier: Intended Audience :: Science/Research
Classifier: License :: OSI Approved :: BSD License
Classifier: Operating System :: OS Independent
Classifier: Programming Language :: Python :: 3.9
Classifier: Programming Language :: Python :: 3.10
Classifier: Programming Language :: Python :: 3.11
Classifier: Programming Language :: Python :: 3.12
Classifier: Programming Language :: Python :: 3.13
Classifier: Programming Language :: Python :: 3.14
Classifier: Topic :: Scientific/Engineering :: Physics
Requires-Python: <3.15,>=3.9
Requires-Dist: ase<=3.27.0,>=3.22.1
Requires-Dist: numpy<=2.4.1,>=1.26.0
Requires-Dist: pandas<=3.0.0,>=2.0.3
Requires-Dist: scipy<=1.17.0,>=1.11.1
Provides-Extra: h5md
Requires-Dist: h5py<=3.15.1,>=3.9.0; extra == 'h5md'
